[
  {
    "type": "OPEN",
    "pair": "MATIC/USD",
    "direction": "SHORT",
    "price": 0.182,
    "size": 12375.303456768765,
    "leverage": 16,
    "confidence": 0.7507684097106384,
    "allocated_capital": 2252.305229131915,
    "timestamp": "2025-04-15T17:27:28.716698"
  },
  {
    "type": "OPEN",
    "pair": "ATOM/USD",
    "direction": "SHORT",
    "price": 4.0773,
    "size": 437.5403581575242,
    "leverage": 15,
    "confidence": 0.6701277077944753,
    "allocated_capital": 1783.9833023156737,
    "timestamp": "2025-04-15T17:27:34.166346"
  }
]